pts_lab_smp_psu/__init__.py
pts_lab_smp_psu/lab_smp_psu.py
pts_lab_smp_psu-0.0.1.dist-info/LICENSE.txt
pts_lab_smp_psu-0.0.1.dist-info/METADATA
pts_lab_smp_psu-0.0.1.dist-info/WHEEL
pts_lab_smp_psu-0.0.1.dist-info/top_level.txt
pts_lab_smp_psu-0.0.1.dist-info/RECORD
