Metadata-Version: 2.1
Name: pts-lab-smp-psu
Version: 0.0.1
Summary: LAB-SMP PSU Diagnostic Package
Home-page: https://gitlab.com/pass-testing-solutions/lab-smp-psu
Author: Pass testing Solutions GmbH
Author-email: shuparna@pass-testing.de
License: MIT
Classifier: License :: OSI Approved :: MIT License
Classifier: Programming Language :: Python :: 3
Classifier: Programming Language :: Python :: 3.9
License-File: LICENSE.txt
